street_view_randomizer/arg_parser.py
street_view_randomizer/coordinate.py
street_view_randomizer/countries.py
street_view_randomizer/main.py
street_view_randomizer/street_view_static_api.py
street_view_randomizer-0.1.0.dist-info/LICENSE
street_view_randomizer-0.1.0.dist-info/METADATA
street_view_randomizer-0.1.0.dist-info/WHEEL
street_view_randomizer-0.1.0.dist-info/entry_points.txt
street_view_randomizer-0.1.0.dist-info/top_level.txt
street_view_randomizer-0.1.0.dist-info/RECORD
