Metadata-Version: 2.1
Name: street-view-randomizer
Version: 0.1.0
Summary: Generate random Google Street View images from all around the world
Author-email: Diego Paiva <diego.paiva13@gmail.com>
License: MIT License
Project-URL: Homepage, https://github.com/diegopaiva1/street-view-randomizer
Project-URL: Bug Tracker, https://github.com/diegopaiva1/street-view-randomizer/issues
Keywords: google,street view,api,random,images
Classifier: Programming Language :: Python :: 3
Classifier: License :: OSI Approved :: MIT License
Classifier: Environment :: Console
Classifier: Operating System :: OS Independent
Requires-Python: >=3.6
License-File: LICENSE
